{"id":150,"name":"VS\u010cR V\u011bznice M\u00edrov","nickname":"M\u00edrov","description":"V\u011bznice M\u00edrov je v\u011bznice um\u00edst\u011bn\u00e1 na b\u00fdval\u00e9m st\u0159edov\u011bk\u00e9m hrad\u011b v obci M\u00edrov (okres \u0160umperk). Jde o v\u011bznici se zv\u00fd\u0161enou ostrahou, kter\u00e1 m\u00e1 mimo jin\u00e9 odd\u011blen\u00ed pro do\u017eivotn\u011b odsouzen\u00e9, v n\u011bm\u017e jsou v\u011bzn\u011bni nejnebezpe\u010dn\u011bj\u0161\u00ed v\u011bzni \u010cesk\u00e9 republiky.\r\nJeho asi nejslavn\u011bj\u0161\u00edm v\u011bzn\u011bm byl Ji\u0159\u00ed Kaj\u00ednek, jednak pro nejasnosti ve sv\u00e9m procesu, jednak (a zejm\u00e9na) kv\u016fli tomu, \u017ee v roce 2000 z M\u00edrova uprchl a byl dopaden a\u017e po n\u011bkolika t\u00fddnech. Kaj\u00ednek byl z\u0159ejm\u011b jedin\u00fdm v\u011bzn\u011bm, kter\u00e9mu se poda\u0159ilo z v\u011bznice uprchnout. Spolu s n\u00edm m\u011bl ut\u00e9ci i dal\u0161\u00ed do\u017eivotn\u011b odsouzen\u00fd vrah Martin Vlas\u00e1k, ten se v\u0161ak zalekl st\u0159elby a vr\u00e1til se do cely.\r\nZa protektor\u00e1tu \u010cechy a Morava slou\u017eila v\u011bznice jako \u201eOzdravovna pro plicn\u011b chor\u00e9 v\u011bzn\u011b slovansk\u00fdch n\u00e1rodnost\u00ed\u201c, zvl\u00e1\u0161t\u011b \u010cechy a Pol\u00e1ky. Byli zde v\u011bzn\u011bni n\u011bkte\u0159\u00ed odboj\u00e1\u0159i. Za komunistick\u00e9ho re\u017eimu byla m\u00edrovsk\u00e1 v\u011bznice pova\u017eov\u00e1na za jedno z nejkrut\u011bj\u0161\u00edch v\u011bzen\u00ed pro politick\u00e9 v\u011bzn\u011b, se kter\u00fdmi zde bylo zach\u00e1zeno h\u016f\u0159e ne\u017e s nejt\u011b\u017e\u0161\u00edmi zlo\u010dinci. B\u011b\u017en\u00e9 bylo odep\u00edr\u00e1n\u00ed kontaktu s rodinou, odep\u00edr\u00e1n\u00ed l\u00e9\u010dby a l\u00e9k\u016f a krut\u00e9 mu\u010den\u00ed, kter\u00e9 bylo p\u0159\u00ed\u010dinou \u00famrt\u00ed \u0159ady v\u011bz\u0148\u016f.","source":"cs.wikipedia.org","sourceURL":"https:\/\/cs.wikipedia.org\/wiki\/V%C4%9Bznice_M%C3%ADrov","website":"https:\/\/www.vscr.cz\/veznice-mirov","address":"M\u00edrov 27 789 53 M\u00edrov","postal_address":"P. O. Box","postal_housenumber":"1","city":"M\u00edrov","zip":"78953","phone":"583488111","gps":"49.796174, 16.845937","map_point":null,"google_url":"https:\/\/www.google.com\/maps\/place\/V\u011bznice+M%C3%ADrov+v\u011bze\u0148sk\u00e1+slu\u017eba+\u010cR\/@49.7962915,16.8439759,17z\/data=!3m1!4b1!4m5!3m4!1s0x471212c33c046d4b:0x4a82a41d28fc80e8!8m2!3d49.7962881!4d16.8461646","bann":0,"mapmarker":{"top":47.14,"left":67.95},"place_image":"https:\/\/www.smsdobasy.cz\/st\/html\/img\/places\/headers\/.jpg"}